alibabacloud_ram20150501/__init__.py
alibabacloud_ram20150501/client.py
alibabacloud_ram20150501/models.py
alibabacloud_ram20150501-1.2.0.dist-info/LICENSE
alibabacloud_ram20150501-1.2.0.dist-info/METADATA
alibabacloud_ram20150501-1.2.0.dist-info/WHEEL
alibabacloud_ram20150501-1.2.0.dist-info/top_level.txt
alibabacloud_ram20150501-1.2.0.dist-info/RECORD
